hellbox/__init__.py
hellbox/__version__.py
hellbox/autoimporter.py
hellbox/chute.py
hellbox/hellbox.py
hellbox/source_file.py
hellbox/task.py
hellbox/chutes/composite.py
hellbox/jobs/__init__.py
hellbox-0.1.3.dist-info/LICENSE
hellbox-0.1.3.dist-info/METADATA
hellbox-0.1.3.dist-info/WHEEL
hellbox-0.1.3.dist-info/top_level.txt
hellbox-0.1.3.dist-info/RECORD
