Metadata-Version: 2.1
Name: hellbox
Version: 0.1.3
Summary: Build system for font development.
Home-page: http://github.com/hellboxpy/hellbox
Author: Jack Jennings
Author-email: jack@standard-library.com
License: MIT
Platform: UNKNOWN
Classifier: License :: OSI Approved :: MIT License
Classifier: Development Status :: 3 - Alpha
Classifier: Topic :: Software Development :: Build Tools
Classifier: Programming Language :: Python
Classifier: Programming Language :: Python :: 3
Classifier: Programming Language :: Python :: 3.6
Classifier: Programming Language :: Python :: 3.7
Classifier: Programming Language :: Python :: Implementation :: CPython
Requires-Python: >=3.6.0
Requires-Dist: glob2
